Metadata-Version: 2.2
Name: itsai-data-engine
Version: 0.1.3
Summary: Conversational AI for Structured Data
Requires-Python: >=3.12
Requires-Dist: duckdb>=1.1.3
Requires-Dist: duckdb-engine>=0.14.0
Requires-Dist: pandas[excel]>=2.2.2
Requires-Dist: sqlalchemy-bigquery>=1.12.0
Requires-Dist: sqlalchemy>=2.0.3
Requires-Dist: langchain-openai>=0.1.11
Requires-Dist: azure-search-documents>=11.4
Requires-Dist: azure-identity>=1.17.0
Requires-Dist: python-dotenv>=1.0.1
Requires-Dist: jinja2>=3.1.5
Requires-Dist: langchain-community>=0.2.6
Requires-Dist: langchain-google-vertexai>=1.0.4
